daya_ai/__init__.py
daya_ai/_version.py
daya_ai/core.py
daya_ai-0.1.0.dist-info/licenses/LICENSE
daya_ai-0.1.0.dist-info/METADATA
daya_ai-0.1.0.dist-info/WHEEL
daya_ai-0.1.0.dist-info/top_level.txt
daya_ai-0.1.0.dist-info/RECORD
