Metadata-Version: 2.4
Name: daya_ai
Version: 0.1.0
Summary: AI helper functions
Author: Daya Mathew
License: MIT
Project-URL: Homepage, https://example.com
Requires-Python: >=3.9
License-File: LICENSE
Requires-Dist: openai
Dynamic: license-file
